.DS_Store
ledfx/__init__.py
ledfx/__main__.py
ledfx/color.py
ledfx/config.py
ledfx/consts.py
ledfx/core.py
ledfx/default_presets.yaml
ledfx/events.py
ledfx/http.py
ledfx/utils.py
ledfx/api/__init__.py
ledfx/api/audio_devices.py
ledfx/api/config.py
ledfx/api/device.py
ledfx/api/device_effects.py
ledfx/api/device_presets.py
ledfx/api/devices.py
ledfx/api/effect.py
ledfx/api/effects.py
ledfx/api/find_devices.py
ledfx/api/graphics_quality.py
ledfx/api/info.py
ledfx/api/presets.py
ledfx/api/scenes.py
ledfx/api/schema.py
ledfx/api/schema_types.py
ledfx/api/utils.py
ledfx/api/websocket.py
ledfx/devices/FXMatrix.py
ledfx/devices/__init__.py
ledfx/devices/e131.py
ledfx/devices/udp.py
ledfx/effects/__init__.py
ledfx/effects/audio.py
ledfx/effects/bands(Reactive).py
ledfx/effects/bar(Reactive).py
ledfx/effects/blocks(Reactive).py
ledfx/effects/energy(Reactive).py
ledfx/effects/equalizer(reactive).py
ledfx/effects/fade.py
ledfx/effects/gradient.py
ledfx/effects/magnitude(Reactive).py
ledfx/effects/math.py
ledfx/effects/mel.py
ledfx/effects/modulate.py
ledfx/effects/multiBar(Reactive).py
ledfx/effects/pitchSpectrum(Reactive).py
ledfx/effects/power(Reactive).py
ledfx/effects/rain(Reactive).py
ledfx/effects/rainbow.py
ledfx/effects/scroll(Reactive).py
ledfx/effects/singleColor.py
ledfx/effects/spectrum(Reactive).py
ledfx/effects/strobe(Reactive).py
ledfx/effects/temporal.py
ledfx/effects/wavelength(Reactive).py
ledfx/effects/effectlets/__init__.py
ledfx/effects/effectlets/droplet_0.npy
ledfx/effects/effectlets/droplet_1.npy
ledfx/effects/effectlets/droplet_2.npy
ledfx/frontend/components/SceneCard/SceneConfigTable.jsx
ledfx_frontend/.DS_Store
ledfx_frontend/__init__.py
ledfx_frontend/asset-manifest.json
ledfx_frontend/favicon.ico
ledfx_frontend/index.html
ledfx_frontend/logo192.png
ledfx_frontend/logo512.png
ledfx_frontend/precache-manifest.b20253c4725abce969d00ebfad32158c.js
ledfx_frontend/precache-manifest.e9ae62f81b31cb53a3367dff6cfd0b39.js
ledfx_dev-0.9.0.dist-info/AUTHORS.rst
ledfx_dev-0.9.0.dist-info/LICENSE.txt
ledfx_dev-0.9.0.dist-info/METADATA
ledfx_dev-0.9.0.dist-info/WHEEL
ledfx_dev-0.9.0.dist-info/entry_points.txt
ledfx_dev-0.9.0.dist-info/top_level.txt
ledfx_dev-0.9.0.dist-info/zip-safe
ledfx_dev-0.9.0.dist-info/RECORD
