Metadata-Version: 2.1
Name: ledfx-dev
Version: 0.9.0
Summary: A network based light effect controller
Home-page: https://github.com/ahodges9/LedFx/tree/dev
Author: Austin Hodges
Author-email: austin.b.hodges@gmail.com
Maintainer: LedFx Devs
Maintainer-email: ledfx.app@gmail.com
License: The MIT License
Project-URL: Documentation, https://ledfx.readthedocs.io/en/docs/index.html
Project-URL: Website, https://ledfx.app
Project-URL: Source, https://github.com/ahodges9/LedFx
Project-URL: Discord, https://discord.gg/PqXMuthSNx
Platform: any
Classifier: Development Status :: 2 - Pre-Alpha
Classifier: Programming Language :: Python :: 3
Classifier: Programming Language :: Python :: 3.7
Classifier: Programming Language :: Python :: 3.8
Classifier: Programming Language :: Python :: 3.9
Classifier: License :: OSI Approved :: MIT License
Classifier: Natural Language :: English
Requires-Python: >=3.7.0
Requires-Dist: numpy (==1.19.3)
Requires-Dist: voluptuous (==0.12.0)
Requires-Dist: pyaudio (>=0.2.11)
Requires-Dist: sacn (==1.4.6)
Requires-Dist: aiohttp (==3.6.3)
Requires-Dist: yarl (==1.5.1)
Requires-Dist: multidict (==4.7.6)
Requires-Dist: aiohttp-jinja2 (>=1.1.0)
Requires-Dist: requests (>=2.24.0)
Requires-Dist: pyyaml (>=5.3.1)
Requires-Dist: aubio (>=0.4.9)
Requires-Dist: zeroconf (>=0.28.6)
Requires-Dist: pyupdater (>=3.1.1)
Requires-Dist: pypiwin32 (>=223) ; platform_system == "Windows"
